AUTHORS
CHANGELOG
INSTALL
LICENSE
MANIFEST.in
README
setup.py
django_htmlsanitizer.egg-info/PKG-INFO
django_htmlsanitizer.egg-info/SOURCES.txt
django_htmlsanitizer.egg-info/dependency_links.txt
django_htmlsanitizer.egg-info/not-zip-safe
django_htmlsanitizer.egg-info/requires.txt
django_htmlsanitizer.egg-info/top_level.txt
htmlsanitizer/__init__.py
htmlsanitizer/models.py
htmlsanitizer/testsettings.py
htmlsanitizer/templatetags/__init__.py
htmlsanitizer/templatetags/htmlsanitizer_tags.py
htmlsanitizer/tests/__init__.py
htmlsanitizer/utils/__init__.py
htmlsanitizer/utils/constants.py
htmlsanitizer/utils/escape.py
htmlsanitizer/utils/sanitizer.py