Metadata-Version: 1.0
Name: django-htmlsanitizer
Version: 10.10
Summary: @TODO
Home-page: http://pypi.python.org/pypi/django-htmlsanitizer
Author: Co-Capacity
Author-email: django-htmlsanitizer@co-capacity.org
License: UNKNOWN
Platform: UNKNOWN
Classifier: Development Status :: 4 - Beta
Classifier: Environment :: Web Environment
Classifier: Framework :: Django
Classifier: Intended Audience :: Developers
Classifier: License :: OSI Approved :: BSD License
Classifier: Operating System :: OS Independent
Classifier: Programming Language :: Python
Classifier: Topic :: Internet :: WWW/HTTP
